[
  {
    "name": "alpha_001_quality_reversal",
    "expr": "add(rank(divide(cashflow_op, assets)), rank(divide(ebit, assets))) - rank(ts_delta(close, 5))",
    "setting": {
      "instrumentType": "EQUITY",
      "region": "USA",
      "universe": "TOP3000",
      "delay": 1,
      "decay": 2,
      "neutralization": "SUBINDUSTRY",
      "truncation": 0.08,
      "pasteurization": "ON",
      "unitHandling": "VERIFY",
      "nanHandling": "OFF",
      "language": "FASTEXPR",
      "visualization": false
    }
  },
  {
    "name": "alpha_002_fcf_margin_reversal",
    "expr": "add(rank(divide(subtract(cashflow_op, capex), assets)), rank(divide(ebitda, enterprise_value))) - rank(ts_mean(ts_delta(close, 3), 3))",
    "setting": {
      "instrumentType": "EQUITY",
      "region": "USA",
      "universe": "TOP3000",
      "delay": 1,
      "decay": 3,
      "neutralization": "SUBINDUSTRY",
      "truncation": 0.08,
      "pasteurization": "ON",
      "unitHandling": "VERIFY",
      "nanHandling": "OFF",
      "language": "FASTEXPR",
      "visualization": false
    }
  },
  {
    "name": "alpha_003_est_quality_reversal",
    "expr": "add(rank(divide(est_cashflow_op, est_tot_assets)), rank(divide(est_ebit, est_tot_assets))) - rank(ts_delta(close, 10))",
    "setting": {
      "instrumentType": "EQUITY",
      "region": "USA",
      "universe": "TOP3000",
      "delay": 1,
      "decay": 4,
      "neutralization": "SUBINDUSTRY",
      "truncation": 0.08,
      "pasteurization": "ON",
      "unitHandling": "VERIFY",
      "nanHandling": "OFF",
      "language": "FASTEXPR",
      "visualization": false
    }
  },
  {
    "name": "alpha_004_balance_sheet_reversal",
    "expr": "add(rank(divide(cash, assets)), rank(divide(equity, assets))) - add(rank(divide(debt, assets)), rank(ts_delta(close, 5)))",
    "setting": {
      "instrumentType": "EQUITY",
      "region": "USA",
      "universe": "TOP3000",
      "delay": 1,
      "decay": 2,
      "neutralization": "SUBINDUSTRY",
      "truncation": 0.08,
      "pasteurization": "ON",
      "unitHandling": "VERIFY",
      "nanHandling": "OFF",
      "language": "FASTEXPR",
      "visualization": false
    }
  },
  {
    "name": "alpha_005_analyst_quality_reversal",
    "expr": "add(rank(divide(anl4_cfo_value, assets)), rank(divide(anl4_ebit_value, assets))) - rank(ts_mean(ts_delta(close, 7), 2))",
    "setting": {
      "instrumentType": "EQUITY",
      "region": "USA",
      "universe": "TOP3000",
      "delay": 1,
      "decay": 3,
      "neutralization": "SUBINDUSTRY",
      "truncation": 0.08,
      "pasteurization": "ON",
      "unitHandling": "VERIFY",
      "nanHandling": "OFF",
      "language": "FASTEXPR",
      "visualization": false
    }
  },
  {
    "name": "alpha_006_profit_stability_reversal",
    "expr": "add(rank(divide(netprofit, assets)), negate(rank(ts_std_dev(close, 20)))) - rank(ts_delta(close, 4))",
    "setting": {
      "instrumentType": "EQUITY",
      "region": "USA",
      "universe": "TOP3000",
      "delay": 1,
      "decay": 2,
      "neutralization": "SUBINDUSTRY",
      "truncation": 0.08,
      "pasteurization": "ON",
      "unitHandling": "VERIFY",
      "nanHandling": "OFF",
      "language": "FASTEXPR",
      "visualization": false
    }
  }
]