[
  {
    "alpha_id": "E5rnYxlm",
    "expr": "rank(add(add(multiply(0.3, reverse(ts_std_dev(ts_backfill(actual_eps_value_quarterly, 126), 168))), multiply(0.5, ts_zscore(subtract(ts_mean(close, 3), close), 20))), multiply(0.2, ts_zscore(ts_backfill(return_equity, 126), 252))))",
    "grade": "INFERIOR",
    "stage": "IS",
    "status": "UNSUBMITTED",
    "sharpe": 1.67,
    "fitness": 0.92,
    "turnover": 0.2559,
    "returns": 0.0784,
    "drawdown": 0.0474,
    "margin": 0.000613,
    "checks_pass": false,
    "checks_detail": [
      {
        "name": "LOW_SHARPE",
        "result": "PASS",
        "value": 1.67,
        "limit": 1.25,
        "message": null
      },
      {
        "name": "LOW_FITNESS",
        "result": "FAIL",
        "value": 0.92,
        "limit": 1.0,
        "message": null
      },
      {
        "name": "LOW_TURNOVER",
        "result": "PASS",
        "value": 0.2559,
        "limit": 0.01,
        "message": null
      },
      {
        "name": "HIGH_TURNOVER",
        "result": "PASS",
        "value": 0.2559,
        "limit": 0.7,
        "message": null
      },
      {
        "name": "CONCENTRATED_WEIGHT",
        "result": "PASS",
        "value": null,
        "limit": null,
        "message": null
      },
      {
        "name": "LOW_SUB_UNIVERSE_SHARPE",
        "result": "PASS",
        "value": 0.92,
        "limit": 0.72,
        "message": null
      },
      {
        "name": "UNITS",
        "result": "WARNING",
        "value": null,
        "limit": null,
        "message": "Incompatible unit for input of \"ts_backfill\" at index 0, expected \"Unit[TSPrice:1,TSShare:1]\", found \"Unit[CSPrice:1,CSShare:1,Group:1]\""
      },
      {
        "name": "SELF_CORRELATION",
        "result": "PENDING",
        "value": null,
        "limit": null,
        "message": null
      },
      {
        "name": "MATCHES_COMPETITION",
        "result": "PASS",
        "value": null,
        "limit": null,
        "message": null
      }
    ],
    "weight_max": null,
    "sub_univ_sharpe": 0.92,
    "self_corr": null,
    "error": null,
    "field_id": "alpha_142_eps_stable_rebound_roe_subind",
    "settings_used": {
      "instrumentType": "EQUITY",
      "region": "USA",
      "universe": "TOP3000",
      "delay": 1,
      "decay": 8,
      "neutralization": "SUBINDUSTRY",
      "truncation": 0.05,
      "pasteurization": "ON",
      "unitHandling": "VERIFY",
      "nanHandling": "OFF",
      "language": "FASTEXPR",
      "visualization": false
    },
    "judge": {
      "verdict": "PASS",
      "comment": "以下是对该 BRAIN alpha 的简要评估：\n\n### 1. Sharpe\n- **Sharpe = 1.67**\n- 表现 **一般偏弱**。通常可提交的 alpha 往往需要更高的 Sharpe，这个值说明信号有一定有效性，但优势不够明显，抗噪声能力有限。\n\n### 2. Turnover\n- **Turnover = 0.2559**\n- 换手率 **适中偏低**，这一点是比较好的，说明信号相对稳定，不属于过度交易型 alpha，有利于实盘执行和降低交易成本。\n\n### 3. Drawdown\n- **Drawdown = 0.0474**\n- 回撤 **控制尚可**，不算大，说明风险暴露没有特别激进，这一点是正面的。\n\n### 4. Fitness\n- **Fitness = 0.92**\n- Fitness **偏低**。通常这是一个比较关键的问题，说明综合质量不够强，可能稳定性、泛化能力或收益效率不足。\n\n---\n\n## 是否值得提交\n- **结论：FAIL**\n\n### 理由\n- 虽然 **Turnover** 和 **Drawdown** 还可以，\n- 但 **Sharpe 不够强，Fitness 低于理想水平**，\n- 且结果中明确显示 **grade = \"INFERIOR\"**、**checks_pass = false**，\n- 因此当前版本 **不建议提交**。\n\n---\n\n## 改进建议\n1. **提升因子纯度**\n   - 当前表达式混合了 EPS 稳定性、短期价格反转、ROE 三部分，可能存在信号稀释。\n   - 建议拆分测试每个子因子单独效果，确认真正贡献来源。\n\n2. **弱化短周期价格项噪声**\n   - `ts_zscore(subtract(ts_mean(close, 3), close), 20)` 带有较强短期反转特征，容易引入噪声。\n   - 可尝试拉长窗口，或改成更平滑的动量/反转定义。\n\n3. **增强基本面信号区分度**\n   - `actual_eps_value_quarterly` 和 `return_equity` 都用了 `backfill`，可能导致截面差异被削弱。\n   - 可以尝试加入变化率、同比改善、加速度等形式，而不仅是水平或稳定性。\n\n4. **加入行业/子行业中性化**\n   - 从名字看有 `subind`，但表达式里未明显体现中性化处理。\n   - 建议做 **subindustry neutralization**，避免行业暴露主导收益。\n\n5. **重新优化权重**\n   - 当前权重 `0.3 / 0.5 / 0.2` 可能使价格因子占比过高。\n   - 建议网格搜索或分层测试，寻找更优组合，尤其提高基本面部分的贡献。\n\n如果你愿意，我也可以进一步帮你把这个 alpha **改写成几个更可能通过 checks 的候选版本**。"
    }
  },
  {
    "alpha_id": "LLloqYEn",
    "expr": "rank(add(add(multiply(0.3, reverse(ts_std_dev(ts_backfill(actual_eps_value_quarterly, 126), 168))), multiply(0.5, ts_zscore(reverse(ts_delta(close, 3)), 20))), multiply(0.2, ts_zscore(ts_backfill(return_equity, 126), 252))))",
    "grade": "INFERIOR",
    "stage": "IS",
    "status": "UNSUBMITTED",
    "sharpe": 1.34,
    "fitness": 0.74,
    "turnover": 0.2698,
    "returns": 0.0812,
    "drawdown": 0.0717,
    "margin": 0.000602,
    "checks_pass": false,
    "checks_detail": [
      {
        "name": "LOW_SHARPE",
        "result": "PASS",
        "value": 1.34,
        "limit": 1.25,
        "message": null
      },
      {
        "name": "LOW_FITNESS",
        "result": "FAIL",
        "value": 0.74,
        "limit": 1.0,
        "message": null
      },
      {
        "name": "LOW_TURNOVER",
        "result": "PASS",
        "value": 0.2698,
        "limit": 0.01,
        "message": null
      },
      {
        "name": "HIGH_TURNOVER",
        "result": "PASS",
        "value": 0.2698,
        "limit": 0.7,
        "message": null
      },
      {
        "name": "CONCENTRATED_WEIGHT",
        "result": "PASS",
        "value": null,
        "limit": null,
        "message": null
      },
      {
        "name": "LOW_SUB_UNIVERSE_SHARPE",
        "result": "PASS",
        "value": 0.77,
        "limit": 0.58,
        "message": null
      },
      {
        "name": "UNITS",
        "result": "WARNING",
        "value": null,
        "limit": null,
        "message": "Incompatible unit for input of \"ts_backfill\" at index 0, expected \"Unit[TSPrice:1,TSShare:1]\", found \"Unit[CSPrice:1,CSShare:1,Group:1]\""
      },
      {
        "name": "SELF_CORRELATION",
        "result": "PENDING",
        "value": null,
        "limit": null,
        "message": null
      },
      {
        "name": "MATCHES_COMPETITION",
        "result": "PASS",
        "value": null,
        "limit": null,
        "message": null
      }
    ],
    "weight_max": null,
    "sub_univ_sharpe": 0.77,
    "self_corr": null,
    "error": null,
    "field_id": "alpha_141_eps_stable_delta_rebound_roe",
    "settings_used": {
      "instrumentType": "EQUITY",
      "region": "USA",
      "universe": "TOP3000",
      "delay": 1,
      "decay": 7,
      "neutralization": "INDUSTRY",
      "truncation": 0.06,
      "pasteurization": "ON",
      "unitHandling": "VERIFY",
      "nanHandling": "OFF",
      "language": "FASTEXPR",
      "visualization": false
    },
    "judge": {
      "verdict": "PASS",
      "comment": "**结论：FAIL**\n\n### 简短评价\n\n- **Sharpe: 1.34**  \n  有一定预测能力，但不算强。在 BRAIN 环境里通常只能算中等偏弱，离“稳健可提交通常标准”还有差距。\n\n- **Turnover: 0.2698**  \n  换手适中，不算过高，这点是相对不错的，说明信号持有期还可以，没有明显交易摩擦过大的问题。\n\n- **Drawdown: 0.0717**  \n  回撤控制尚可，7% 左右不算差，风险表现中规中矩，没有特别大的风控隐患。\n\n- **Fitness: 0.74**  \n  偏低。Fitness 往往比单看 Sharpe 更能反映综合质量，0.74 说明 alpha 的稳定性、可实现性或泛化能力不足，这也是未通过 checks 的一个危险信号。\n\n### 是否值得提交\n- **FAIL**\n\n虽然 Sharpe、回撤、换手都不算很差，但**Fitness 偏低且 checks_pass = false**，再加上 **grade = INFERIOR**，说明该 alpha 目前整体质量不足，不建议直接提交。\n\n### 改进建议\n\n1. **增强核心驱动，减少拼接式因子**\n   - 当前表达式由 **EPS 稳定性 + 短期反转 + ROE** 混合而成，但三者组合看起来偏“直觉拼接”，协同性可能不强。\n   - 建议先单独检验每个子信号的贡献，再决定是否保留。\n\n2. **弱化短期价格反转成分**\n   - `ts_zscore(reverse(ts_delta(close, 3)), 20)` 这类短期反转虽然常见，但容易带来拥挤和不稳定，尤其在不同市场状态下失效。\n   - 可以尝试：\n     - 延长窗口，如 5~10 日；\n     - 改成更平滑的反转/超跌指标；\n     - 降低该项权重。\n\n3. **提升基本面信号的新鲜度和区分度**\n   - `ts_backfill(actual_eps_value_quarterly, 126)` 和 `ts_backfill(return_equity, 126)` 都比较依赖低频财务数据，若处理不当容易造成信号陈旧。\n   - 可尝试：\n     - 使用变化率而非静态水平；\n     - 用 surprise / revision / acceleration 类指标；\n     - 对财务变量做行业中性化或分组标准化。\n\n4. **优化权重结构**\n   - 当前权重是 `0.3 / 0.5 / 0.2`，价格项占比最高，可能掩盖了基本面 alpha。\n   - 建议做参数扫描，测试更均衡或更偏基本面的组合。\n\n5. **检查未通过项**\n   - `checks_pass = false` 非常关键，需重点排查：\n     - 是否存在风格暴露过大；\n     - 是否行业/市值偏置明显；\n     - 是否子阶段表现不稳定；\n     - 是否与已有因子过度相关。\n\n6. **加入中性化与鲁棒处理**\n   - 可考虑加入：\n     - `group_rank` / `group_zscore`\n     - 行业中性化\n     - winsorize / hump / decay\n   - 这些往往能提升 Fitness 和 checks 通过率。\n\n如果你愿意，我可以进一步**直接给你改写 3 个更可能通过的 BRAIN alpha 版本**。"
    }
  },
  {
    "alpha_id": "0mKZdbKK",
    "expr": "rank(add(add(multiply(0.3, reverse(ts_std_dev(ts_backfill(actual_eps_value_quarterly, 126), 168))), multiply(0.5, ts_zscore(subtract(ts_mean(close, 3), close), 20))), multiply(0.2, ts_zscore(ts_backfill(return_equity, 126), 252))))",
    "grade": "INFERIOR",
    "stage": "IS",
    "status": "UNSUBMITTED",
    "sharpe": 1.17,
    "fitness": 0.66,
    "turnover": 0.3647,
    "returns": 0.1163,
    "drawdown": 0.0925,
    "margin": 0.000638,
    "checks_pass": false,
    "checks_detail": [
      {
        "name": "LOW_SHARPE",
        "result": "FAIL",
        "value": 1.17,
        "limit": 1.25,
        "message": null
      },
      {
        "name": "LOW_FITNESS",
        "result": "FAIL",
        "value": 0.66,
        "limit": 1.0,
        "message": null
      },
      {
        "name": "LOW_TURNOVER",
        "result": "PASS",
        "value": 0.3647,
        "limit": 0.01,
        "message": null
      },
      {
        "name": "HIGH_TURNOVER",
        "result": "PASS",
        "value": 0.3647,
        "limit": 0.7,
        "message": null
      },
      {
        "name": "CONCENTRATED_WEIGHT",
        "result": "PASS",
        "value": null,
        "limit": null,
        "message": null
      },
      {
        "name": "LOW_SUB_UNIVERSE_SHARPE",
        "result": "PASS",
        "value": 1.04,
        "limit": 0.62,
        "message": null
      },
      {
        "name": "UNITS",
        "result": "WARNING",
        "value": null,
        "limit": null,
        "message": "Incompatible unit for input of \"ts_backfill\" at index 0, expected \"Unit[TSPrice:1,TSShare:1]\", found \"Unit[CSPrice:1,CSShare:1,Group:1]\""
      },
      {
        "name": "SELF_CORRELATION",
        "result": "PENDING",
        "value": null,
        "limit": null,
        "message": null
      },
      {
        "name": "MATCHES_COMPETITION",
        "result": "PASS",
        "value": null,
        "limit": null,
        "message": null
      }
    ],
    "weight_max": null,
    "sub_univ_sharpe": 1.04,
    "self_corr": null,
    "error": null,
    "field_id": "alpha_143_eps_stable_rebound_roe_market",
    "settings_used": {
      "instrumentType": "EQUITY",
      "region": "USA",
      "universe": "TOP2000",
      "delay": 1,
      "decay": 5,
      "neutralization": "MARKET",
      "truncation": 0.07,
      "pasteurization": "ON",
      "unitHandling": "VERIFY",
      "nanHandling": "OFF",
      "language": "FASTEXPR",
      "visualization": false
    },
    "judge": {
      "verdict": "PASS",
      "comment": "**简要评价**\n\n- **Sharpe = 1.17**  \n  偏弱。一般来说可用，但不算有竞争力，说明风险调整后收益不足，稳定性一般。\n\n- **Turnover = 0.3647**  \n  中等偏高，还算可接受，不是主要问题，但也没有体现出特别好的持有稳定性。\n\n- **Drawdown = 0.0925**  \n  回撤 9.25%，不算特别差，但结合 Sharpe 看，承担了这部分回撤后收益表现仍然不够突出。\n\n- **Fitness = 0.66**  \n  明显偏低。通常这是比较关键的短板，说明综合质量不足。\n\n---\n\n**是否值得提交：FAIL**\n\n原因很直接：  \n- **grade = INFERIOR**\n- **checks_pass = false**\n- Sharpe 和 Fitness 都不够好，整体没有达到值得提交的水平。\n\n---\n\n**改进建议**\n\n1. **减少因子拼接的“弱相关堆叠”**  \n   当前表达式把 EPS 稳定性、短期价格反弹、ROE 混在一起，但三者组合后的协同性不强。建议先分别单测每个子因子，再只保留真正有独立增益的部分。\n\n2. **优化价格项，降低短期均值回复噪声**  \n   `ts_zscore(subtract(ts_mean(close, 3), close), 20)` 很像短期反转信号，噪声较大。  \n   可尝试：\n   - 拉长窗口，如 5~10 日均值偏离\n   - 加入波动率归一化\n   - 用 returns 替代 close 直接构造更稳健的 reversal\n\n3. **提升基本面信号时效性**  \n   `ts_backfill(...,126)` 会让季频数据显得比较“陈旧”。可以尝试：\n   - 缩短 backfill 窗口\n   - 对财务字段做变化率/加速度，而不只是水平值\n   - 引入 surprise / revision 类信息增强响应速度\n\n4. **控制基本面因子的极端值影响**  \n   对 `actual_eps_value_quarterly` 和 `return_equity` 建议增加 winsorize / zscore / group neutralize，避免行业或极端财务值主导排序。\n\n5. **做行业/市值中性化**  \n   该因子含有盈利能力和盈利稳定性暴露，容易带入行业和质量风格偏置。建议测试：\n   - `group_neutralize(..., industry)`\n   - 市值中性化  \n   这通常有助于提升 Sharpe 和 checks 表现。\n\n6. **重新分配权重**  \n   当前权重 `0.3 / 0.5 / 0.2` 里价格反弹项占比最高，但它可能正是噪声来源。建议降低价格项权重，提升更稳健的基本面项占比，或通过历史 IC/IR 来定权。\n\n---\n\n**结论**  \n这个 alpha **当前不建议提交（FAIL）**。优先提升 **Fitness 和 Sharpe**，并解决 **checks_pass = false** 的问题，再考虑提交。"
    }
  },
  {
    "alpha_id": "78KPQ8Vb",
    "expr": "rank(add(add(multiply(0.3, reverse(ts_std_dev(ts_backfill(actual_eps_value_quarterly, 126), 168))), multiply(0.5, ts_zscore(subtract(ts_mean(close, 3), close), 20))), multiply(0.2, ts_zscore(ts_backfill(return_equity, 126), 504))))",
    "grade": "INFERIOR",
    "stage": "IS",
    "status": "UNSUBMITTED",
    "sharpe": 1.48,
    "fitness": 0.78,
    "turnover": 0.3289,
    "returns": 0.0921,
    "drawdown": 0.0592,
    "margin": 0.00056,
    "checks_pass": false,
    "checks_detail": [
      {
        "name": "LOW_SHARPE",
        "result": "PASS",
        "value": 1.48,
        "limit": 1.25,
        "message": null
      },
      {
        "name": "LOW_FITNESS",
        "result": "FAIL",
        "value": 0.78,
        "limit": 1.0,
        "message": null
      },
      {
        "name": "LOW_TURNOVER",
        "result": "PASS",
        "value": 0.3289,
        "limit": 0.01,
        "message": null
      },
      {
        "name": "HIGH_TURNOVER",
        "result": "PASS",
        "value": 0.3289,
        "limit": 0.7,
        "message": null
      },
      {
        "name": "CONCENTRATED_WEIGHT",
        "result": "PASS",
        "value": null,
        "limit": null,
        "message": null
      },
      {
        "name": "LOW_SUB_UNIVERSE_SHARPE",
        "result": "PASS",
        "value": 0.84,
        "limit": 0.64,
        "message": null
      },
      {
        "name": "UNITS",
        "result": "WARNING",
        "value": null,
        "limit": null,
        "message": "Incompatible unit for input of \"ts_backfill\" at index 0, expected \"Unit[TSPrice:1,TSShare:1]\", found \"Unit[CSPrice:1,CSShare:1,Group:1]\""
      },
      {
        "name": "SELF_CORRELATION",
        "result": "PENDING",
        "value": null,
        "limit": null,
        "message": null
      },
      {
        "name": "MATCHES_COMPETITION",
        "result": "PASS",
        "value": null,
        "limit": null,
        "message": null
      }
    ],
    "weight_max": null,
    "sub_univ_sharpe": 0.84,
    "self_corr": null,
    "error": null,
    "field_id": "alpha_144_eps_stable_rebound_roe_longroe",
    "settings_used": {
      "instrumentType": "EQUITY",
      "region": "USA",
      "universe": "TOP3000",
      "delay": 1,
      "decay": 6,
      "neutralization": "INDUSTRY",
      "truncation": 0.08,
      "pasteurization": "ON",
      "unitHandling": "VERIFY",
      "nanHandling": "OFF",
      "language": "FASTEXPR",
      "visualization": false
    },
    "judge": {
      "verdict": "PASS",
      "comment": "**简评**\n\n- **Sharpe: 1.48**  \n  偏弱。通常如果想提交，Sharpe 至少应更有竞争力，1.48 说明有一定有效性，但还不够稳健。\n\n- **Turnover: 0.3289**  \n  中等偏高，但还算可接受。不是主要问题，不过说明信号有一定交易频率，需关注交易成本侵蚀。\n\n- **Drawdown: 0.0592**  \n  回撤不算大，这点是相对不错的，说明风险控制尚可。\n\n- **Fitness: 0.78**  \n  明显偏低。Fitness 不足往往意味着综合质量不够，尤其在稳定性、收益效率或可实现性上存在问题。\n\n**结论：FAIL**\n\n原因很直接：  \n1. **Grade = INFERIOR**  \n2. **checks_pass = false**  \n3. Sharpe 和 Fitness 都不够强，虽然 Drawdown 尚可，但不足以弥补整体质量问题。  \n\n---\n\n**改进建议**\n\n1. **降低因子拼接的“弱相关成分”**  \n   当前表达式混合了：\n   - EPS 稳定性反转\n   - 短期价格反弹\n   - ROE 水平  \n   \n   这三者逻辑上不算特别统一，可能导致信号被稀释。建议先拆开分别测试每个子因子贡献，再决定保留哪些部分。\n\n2. **优化权重，而不是固定经验权重**  \n   现在是 `0.3 / 0.5 / 0.2`，较像拍脑袋设定。建议：\n   - 单独看每个子项 Sharpe / IC\n   - 降低弱项权重\n   - 保留最有解释力的 2 个组件\n\n3. **检查 `actual_eps_value_quarterly` 和 `return_equity` 的时效性/回填问题**  \n   使用 `ts_backfill(...,126)` 可能让基本面信号变钝，甚至带来较强陈旧性。  \n   可尝试：\n   - 缩短 backfill 窗口\n   - 对基本面数据做 `ts_zscore` / `ts_rank`\n   - 用变化率替代静态水平，如 EPS surprise、ROE improvement\n\n4. **弱化过短周期价格反转项**  \n   `ts_zscore(subtract(ts_mean(close, 3), close), 20)` 本质上偏短期反弹/均值回复，容易带来噪声和 turnover。  \n   可尝试：\n   - 拉长到 5–10 天窗口\n   - 换成更稳的中短期残差反转\n   - 加入成交量或波动过滤，减少假反弹\n\n5. **增强风险中性与稳健性**  \n   如果 checks 没过，常见原因包括：\n   - 行业/市值暴露过强\n   - 子区间表现不稳定\n   - 极端值驱动  \n   \n   建议加入：\n   - 行业中性化\n   - size neutral\n   - winsorize / hump / decay 处理\n\n6. **优先提升 Fitness，而不只是收益**  \n   这个 alpha 最大短板是“综合质量不足”。应优先提升稳定性与一致性，而不是单纯追求 returns。\n\n如果你愿意，我可以进一步**逐项拆解这个 expr 的经济含义**，并给你几个更可能通过 BRAIN 检查的改写版本。"
    }
  },
  {
    "alpha_id": "E5rnb0Mm",
    "expr": "rank(add(add(multiply(0.3, reverse(ts_std_dev(ts_backfill(actual_eps_value_quarterly, 252), 168))), multiply(0.5, ts_zscore(subtract(ts_mean(close, 3), close), 20))), multiply(0.2, ts_zscore(ts_backfill(return_equity, 126), 252))))",
    "grade": "INFERIOR",
    "stage": "IS",
    "status": "UNSUBMITTED",
    "sharpe": 1.79,
    "fitness": 0.93,
    "turnover": 0.4131,
    "returns": 0.1107,
    "drawdown": 0.0558,
    "margin": 0.000536,
    "checks_pass": false,
    "checks_detail": [
      {
        "name": "LOW_SHARPE",
        "result": "PASS",
        "value": 1.79,
        "limit": 1.25,
        "message": null
      },
      {
        "name": "LOW_FITNESS",
        "result": "FAIL",
        "value": 0.93,
        "limit": 1.0,
        "message": null
      },
      {
        "name": "LOW_TURNOVER",
        "result": "PASS",
        "value": 0.4131,
        "limit": 0.01,
        "message": null
      },
      {
        "name": "HIGH_TURNOVER",
        "result": "PASS",
        "value": 0.4131,
        "limit": 0.7,
        "message": null
      },
      {
        "name": "CONCENTRATED_WEIGHT",
        "result": "PASS",
        "value": null,
        "limit": null,
        "message": null
      },
      {
        "name": "LOW_SUB_UNIVERSE_SHARPE",
        "result": "PASS",
        "value": 1.14,
        "limit": 0.78,
        "message": null
      },
      {
        "name": "UNITS",
        "result": "WARNING",
        "value": null,
        "limit": null,
        "message": "Incompatible unit for input of \"ts_backfill\" at index 0, expected \"Unit[TSPrice:1,TSShare:1]\", found \"Unit[CSPrice:1,CSShare:1,Group:1]\""
      },
      {
        "name": "SELF_CORRELATION",
        "result": "PENDING",
        "value": null,
        "limit": null,
        "message": null
      },
      {
        "name": "MATCHES_COMPETITION",
        "result": "PASS",
        "value": null,
        "limit": null,
        "message": null
      }
    ],
    "weight_max": null,
    "sub_univ_sharpe": 1.14,
    "self_corr": null,
    "error": null,
    "field_id": "alpha_145_eps_smooth_rebound_roe",
    "settings_used": {
      "instrumentType": "EQUITY",
      "region": "USA",
      "universe": "TOP3000",
      "delay": 1,
      "decay": 4,
      "neutralization": "INDUSTRY",
      "truncation": 0.08,
      "pasteurization": "ON",
      "unitHandling": "VERIFY",
      "nanHandling": "ON",
      "language": "FASTEXPR",
      "visualization": false
    },
    "judge": {
      "verdict": "PASS",
      "comment": "**简短评价**\n\n- **Sharpe: 1.79**  \n  中等偏上，但通常还不算很有竞争力。说明有一定风险调整后收益，但离优质 alpha 还有距离。\n\n- **Turnover: 0.4131**  \n  换手适中，不算太高，这点是比较健康的，交易成本压力相对可控。\n\n- **Drawdown: 0.0558**  \n  回撤较低，风险表现不错，说明策略稳定性尚可。\n\n- **Fitness: 0.93**  \n  偏弱。一般 fitness 小于 1 往往说明综合质量不足，可能在稳健性、收益效率或可实现性上不够强。\n\n**是否值得提交：FAIL**\n\n**理由**  \n虽然 **回撤和换手都还可以**，Sharpe 也不算太差，但 **Fitness 低于 1**，且结果中已经显示 **grade = INFERIOR、checks_pass = false**，整体上不满足提交标准，当前版本不建议提交。\n\n**改进建议**\n\n1. **提升信号强度**  \n   当前由 EPS 波动反转、短期价格反弹、ROE 三部分组成，可能逻辑偏分散，建议重新审视各子因子的独立贡献，删除弱贡献项。\n\n2. **优化权重结构**  \n   目前权重为 `0.3 / 0.5 / 0.2`，价格反转占比较高，可能导致 alpha 更偏短期噪声驱动。可尝试降低短期价格项权重，提高基本面项的占比。\n\n3. **增强基本面处理方式**  \n   `actual_eps_value_quarterly` 和 `return_equity` 都用了 backfill，可能引入信号钝化。可尝试：\n   - 用 `ts_delta`、`ts_rank`、`ts_zscore` 提取改善趋势；\n   - 用 surprise / acceleration 类指标替代简单平滑。\n\n4. **降低噪声与提高稳健性**  \n   价格项 `ts_mean(close, 3) - close` 较短，容易受短期扰动影响。可尝试拉长窗口，或改成更稳定的中周期反转/质量确认信号。\n\n5. **检查失败项来源**  \n   既然 `checks_pass = false`，建议优先看具体是哪类检查没过，例如相关性过高、子宇宙不稳定、极端值暴露等，再针对性修正。\n\n如果你愿意，我可以进一步帮你把这条 alpha **改写成 2~3 个更可能通过 BRAIN 检查的候选版本**。"
    }
  },
  {
    "alpha_id": "xAm7Qkrm",
    "expr": "rank(add(add(multiply(0.3, reverse(ts_std_dev(ts_backfill(actual_eps_value_quarterly, 126), 168))), multiply(0.5, ts_zscore(subtract(ts_mean(close, 3), close), 20))), multiply(0.2, ts_zscore(ts_mean(ts_backfill(return_equity, 126), 4), 252))))",
    "grade": "INFERIOR",
    "stage": "IS",
    "status": "UNSUBMITTED",
    "sharpe": 1.58,
    "fitness": 0.89,
    "turnover": 0.3588,
    "returns": 0.1142,
    "drawdown": 0.0599,
    "margin": 0.000637,
    "checks_pass": false,
    "checks_detail": [
      {
        "name": "LOW_SHARPE",
        "result": "PASS",
        "value": 1.58,
        "limit": 1.25,
        "message": null
      },
      {
        "name": "LOW_FITNESS",
        "result": "FAIL",
        "value": 0.89,
        "limit": 1.0,
        "message": null
      },
      {
        "name": "LOW_TURNOVER",
        "result": "PASS",
        "value": 0.3588,
        "limit": 0.01,
        "message": null
      },
      {
        "name": "HIGH_TURNOVER",
        "result": "PASS",
        "value": 0.3588,
        "limit": 0.7,
        "message": null
      },
      {
        "name": "CONCENTRATED_WEIGHT",
        "result": "PASS",
        "value": null,
        "limit": null,
        "message": null
      },
      {
        "name": "LOW_SUB_UNIVERSE_SHARPE",
        "result": "PASS",
        "value": 1.08,
        "limit": 0.68,
        "message": null
      },
      {
        "name": "UNITS",
        "result": "WARNING",
        "value": null,
        "limit": null,
        "message": "Incompatible unit for input of \"ts_backfill\" at index 0, expected \"Unit[TSPrice:1,TSShare:1]\", found \"Unit[CSPrice:1,CSShare:1,Group:1]\""
      },
      {
        "name": "SELF_CORRELATION",
        "result": "PENDING",
        "value": null,
        "limit": null,
        "message": null
      },
      {
        "name": "MATCHES_COMPETITION",
        "result": "PASS",
        "value": null,
        "limit": null,
        "message": null
      }
    ],
    "weight_max": null,
    "sub_univ_sharpe": 1.08,
    "self_corr": null,
    "error": null,
    "field_id": "alpha_147_eps_stable_rebound_smoothroe",
    "settings_used": {
      "instrumentType": "EQUITY",
      "region": "USA",
      "universe": "TOP3000",
      "delay": 1,
      "decay": 5,
      "neutralization": "SECTOR",
      "truncation": 0.07,
      "pasteurization": "ON",
      "unitHandling": "VERIFY",
      "nanHandling": "OFF",
      "language": "FASTEXPR",
      "visualization": false
    },
    "judge": {
      "verdict": "PASS",
      "comment": "**简评**\n\n- **Sharpe = 1.58**  \n  中等偏弱，说明有一定 alpha 能力，但不够突出，离“值得提交”的稳健水平还有差距。\n\n- **Turnover = 0.3588**  \n  换手适中，不算太高，交易层面比较可控，这点是相对正面的。\n\n- **Drawdown = 0.0599**  \n  回撤不大，风险表现尚可，说明信号整体波动不算特别剧烈。\n\n- **Fitness = 0.89**  \n  偏低，通常这是比较关键的问题，意味着综合质量不足，稳定性或收益效率不够好。\n\n**结论：FAIL**\n\n虽然 **Turnover** 和 **Drawdown** 看起来还可以，但 **Sharpe** 不够强，尤其 **Fitness < 1**，再加上结果里明确显示 **grade = INFERIOR**、**checks_pass = false**，因此**不建议提交**。\n\n**改进建议**\n\n1. **提升核心信号强度**  \n   当前 alpha 混合了：\n   - EPS 稳定性反转\n   - 短期价格回撤反转\n   - 平滑 ROE  \n   \n   其中可能存在因子逻辑分散、相互稀释的问题。建议先拆分子因子，分别测试各自 Sharpe 和 Fitness，再决定权重。\n\n2. **优化基本面信号处理**  \n   `actual_eps_value_quarterly` 和 `return_equity` 都经过了较长时间 backfill，可能导致信号过旧。可以尝试：\n   - 缩短 `ts_backfill` 窗口\n   - 对财务变量做 `ts_rank` / `ts_delta` / `ts_zscore`，增强截面区分度\n\n3. **调整反转项参数**  \n   `ts_zscore(subtract(ts_mean(close, 3), close), 20)` 偏短线，可能噪声较大。可尝试：\n   - 改成 5~10 日均价偏离\n   - 或与中期动量/反转结合，降低纯短期噪声\n\n4. **重新分配权重**  \n   当前权重 `0.3 / 0.5 / 0.2` 可能过度依赖价格反转项。建议单独看每一项的边际贡献，降低低效项占比。\n\n5. **加强稳健性检查**  \n   既然 `checks_pass = false`，应重点检查：\n   - 是否存在子周期失效\n   - 行业/市值暴露是否过强\n   - 是否对少数股票或特殊时期过度敏感\n\n如果你愿意，我可以进一步**逐项拆解这个表达式的含义**，并直接给出几个可替换的 BRAIN alpha 改写版本。"
    }
  },
  {
    "alpha_id": "2rnVRL2b",
    "expr": "rank(add(add(multiply(0.3, reverse(ts_std_dev(ts_backfill(actual_eps_value_quarterly, 126), 168))), multiply(0.5, ts_zscore(subtract(ts_mean(close, 5), close), 30))), multiply(0.2, ts_zscore(ts_backfill(return_equity, 126), 252))))",
    "grade": "INFERIOR",
    "stage": "IS",
    "status": "UNSUBMITTED",
    "sharpe": 1.17,
    "fitness": 0.64,
    "turnover": 0.2095,
    "returns": 0.0628,
    "drawdown": 0.0826,
    "margin": 0.000599,
    "checks_pass": false,
    "checks_detail": [
      {
        "name": "LOW_SHARPE",
        "result": "FAIL",
        "value": 1.17,
        "limit": 1.25,
        "message": null
      },
      {
        "name": "LOW_FITNESS",
        "result": "FAIL",
        "value": 0.64,
        "limit": 1.0,
        "message": null
      },
      {
        "name": "LOW_TURNOVER",
        "result": "PASS",
        "value": 0.2095,
        "limit": 0.01,
        "message": null
      },
      {
        "name": "HIGH_TURNOVER",
        "result": "PASS",
        "value": 0.2095,
        "limit": 0.7,
        "message": null
      },
      {
        "name": "CONCENTRATED_WEIGHT",
        "result": "PASS",
        "value": null,
        "limit": null,
        "message": null
      },
      {
        "name": "LOW_SUB_UNIVERSE_SHARPE",
        "result": "PASS",
        "value": 0.85,
        "limit": 0.62,
        "message": null
      },
      {
        "name": "UNITS",
        "result": "WARNING",
        "value": null,
        "limit": null,
        "message": "Incompatible unit for input of \"ts_backfill\" at index 0, expected \"Unit[TSPrice:1,TSShare:1]\", found \"Unit[CSPrice:1,CSShare:1,Group:1]\""
      },
      {
        "name": "SELF_CORRELATION",
        "result": "PENDING",
        "value": null,
        "limit": null,
        "message": null
      },
      {
        "name": "MATCHES_COMPETITION",
        "result": "PASS",
        "value": null,
        "limit": null,
        "message": null
      }
    ],
    "weight_max": null,
    "sub_univ_sharpe": 0.85,
    "self_corr": null,
    "error": null,
    "field_id": "alpha_148_eps_stable_longrebound_roe",
    "settings_used": {
      "instrumentType": "EQUITY",
      "region": "USA",
      "universe": "TOP2000",
      "delay": 1,
      "decay": 9,
      "neutralization": "SUBINDUSTRY",
      "truncation": 0.05,
      "pasteurization": "ON",
      "unitHandling": "VERIFY",
      "nanHandling": "OFF",
      "language": "FASTEXPR",
      "visualization": false
    },
    "judge": {
      "verdict": "PASS",
      "comment": "**简评**\n\n- **Sharpe = 1.17**  \n  偏低，说明风险调整后收益不够强。通常这类水平很难算是有竞争力的 alpha。\n\n- **Turnover = 0.2095**  \n  换手中等偏低，这点是比较好的，说明信号不算特别噪声化，交易成本压力相对可控。\n\n- **Drawdown = 0.0826**  \n  回撤 8.26%，不算很差，但结合 Sharpe 和收益来看，承担这部分回撤并没有换来足够高的回报。\n\n- **Fitness = 0.64**  \n  明显偏弱，通常意味着综合表现不达标，稳定性、收益效率或可实现性不足。\n\n---\n\n**是否值得提交：FAIL**\n\n理由很直接：  \n- **Sharpe 不强**\n- **Fitness 偏低**\n- **grade = INFERIOR**\n- **checks_pass = false**\n\n即使换手和回撤不算特别差，但整体质量不足，当前版本**不建议提交**。\n\n---\n\n**改进建议**\n\n1. **降低因子拼接的“杂糅感”**  \n   当前表达式同时混合了：\n   - EPS 稳定性反转\n   - 短期价格反弹\n   - ROE 水平  \n   逻辑上不是特别统一，可能导致信号互相稀释。建议先拆开做单因子检验，再决定是否组合。\n\n2. **弱化短周期价格反弹项的噪声**  \n   `ts_zscore(subtract(ts_mean(close, 5), close), 30)` 带有较强短期均值回复特征，可能提升噪声。可以尝试：\n   - 拉长窗口，如 10~20 天\n   - 对价格信号做平滑\n   - 改成更稳健的中期反转/超跌指标\n\n3. **提升基本面项的时效性与区分度**  \n   `actual_eps_value_quarterly` 和 `return_equity` 都做了较长 backfill，容易让信号变“陈旧”。建议：\n   - 缩短 backfill 长度\n   - 用变化率/加速度替代静态水平，如 EPS revision、ROE improvement\n   - 加入行业中性化，减少行业暴露\n\n4. **重新优化权重**  \n   当前权重是 `0.3 / 0.5 / 0.2`，价格项占比最高。若目标是做“基本面质量 + 反转”，可以尝试：\n   - 降低价格项权重\n   - 提高基本面稳定性项权重\n   - 用简单网格搜索测试更优组合\n\n5. **做中性化和去极值处理**  \n   如果 checks 没过，常见问题包括集中度、暴露或分布异常。建议进一步做：\n   - 行业中性化\n   - 市值中性化\n   - winsorize / normalize\n   - 检查是否存在少数股票驱动收益\n\n6. **检查 alpha 的真实驱动来源**  \n   建议分别回测三部分子信号：\n   - EPS 稳定性项\n   - 短期反弹项\n   - ROE 项  \n   看看到底是哪一项在贡献收益，哪一项在拖累 Sharpe / Fitness，再决定是否删减。\n\n---\n\n**结论**  \n这个 alpha **目前不值得提交，结论为 FAIL**。建议优先排查 **checks_pass=false** 的原因，并对**短期价格反弹项降噪、基本面项增强时效性、整体做中性化与权重重构**。"
    }
  },
  {
    "alpha_id": "gJoNKjMQ",
    "expr": "rank(add(add(multiply(0.3, reverse(ts_std_dev(ts_backfill(actual_eps_value_quarterly, 126), 168))), multiply(0.5, ts_zscore(subtract(ts_mean(close, 3), close), 20))), multiply(0.2, ts_zscore(ts_backfill(return_equity, 126), 252))))",
    "grade": "INFERIOR",
    "stage": "IS",
    "status": "UNSUBMITTED",
    "sharpe": 1.23,
    "fitness": 0.65,
    "turnover": 0.3028,
    "returns": 0.0833,
    "drawdown": 0.0807,
    "margin": 0.00055,
    "checks_pass": false,
    "checks_detail": [
      {
        "name": "LOW_SHARPE",
        "result": "FAIL",
        "value": 1.23,
        "limit": 1.25,
        "message": null
      },
      {
        "name": "LOW_FITNESS",
        "result": "FAIL",
        "value": 0.65,
        "limit": 1.0,
        "message": null
      },
      {
        "name": "LOW_TURNOVER",
        "result": "PASS",
        "value": 0.3028,
        "limit": 0.01,
        "message": null
      },
      {
        "name": "HIGH_TURNOVER",
        "result": "PASS",
        "value": 0.3028,
        "limit": 0.7,
        "message": null
      },
      {
        "name": "CONCENTRATED_WEIGHT",
        "result": "PASS",
        "value": null,
        "limit": null,
        "message": null
      },
      {
        "name": "LOW_SUB_UNIVERSE_SHARPE",
        "result": "PASS",
        "value": 0.97,
        "limit": 0.65,
        "message": null
      },
      {
        "name": "UNITS",
        "result": "WARNING",
        "value": null,
        "limit": null,
        "message": "Incompatible unit for input of \"ts_backfill\" at index 0, expected \"Unit[TSPrice:1,TSShare:1]\", found \"Unit[CSPrice:1,CSShare:1,Group:1]\""
      },
      {
        "name": "SELF_CORRELATION",
        "result": "PENDING",
        "value": null,
        "limit": null,
        "message": null
      },
      {
        "name": "MATCHES_COMPETITION",
        "result": "PASS",
        "value": null,
        "limit": null,
        "message": null
      }
    ],
    "weight_max": null,
    "sub_univ_sharpe": 0.97,
    "self_corr": null,
    "error": null,
    "field_id": "alpha_146_eps_stable_rebound_roe_top1000",
    "settings_used": {
      "instrumentType": "EQUITY",
      "region": "USA",
      "universe": "TOP1000",
      "delay": 1,
      "decay": 6,
      "neutralization": "INDUSTRY",
      "truncation": 0.09,
      "pasteurization": "ON",
      "unitHandling": "VERIFY",
      "nanHandling": "OFF",
      "language": "FASTEXPR",
      "visualization": false
    },
    "judge": {
      "verdict": "PASS",
      "comment": "**简短评价**\n\n- **Sharpe: 1.23**  \n  偏弱。说明有一定预测能力，但离可提交的优质 alpha 还有明显差距。\n\n- **Turnover: 0.3028**  \n  中等偏高。换手不算失控，但如果收益强度不够，这个换手会拖累实际表现。\n\n- **Drawdown: 0.0807**  \n  回撤中等，可接受，但并不突出。说明策略稳定性一般，没有体现出很强的防御性。\n\n- **Fitness: 0.65**  \n  明显偏低。通常这是比较关键的短板，意味着综合质量不足。\n\n**结论：FAIL**\n\n该 alpha **不值得直接提交**。主要原因是：\n1. **Sharpe 和 Fitness 都不够好**；\n2. **grade = INFERIOR**；\n3. **checks_pass = false**，即使回测指标勉强可看，检查未通过通常也不建议提交。\n\n**改进建议**\n\n1. **降低短期价格反转信号权重**  \n   目前 `ts_mean(close, 3) - close` 这一段偏短期，容易带来噪声和较高换手。可尝试拉长窗口，或改成更平滑的价格偏离/反转定义。\n\n2. **增强基本面信号的“变化率”而不是仅看水平/稳定性**  \n   当前用了 EPS 稳定性和 ROE 水平，但 alpha 可能缺少“改善”维度。可加入：\n   - EPS revision / surprise\n   - ROE 的同比改善\n   - 盈利质量相关指标\n\n3. **对基本面数据做更强的去极值和行业中性化**  \n   `actual_eps_value_quarterly` 和 `return_equity` 容易有行业结构偏置。建议加入：\n   - group neutralization（如行业/子行业）\n   - winsorize / zscore 后再组合\n\n4. **重新调整权重**  \n   当前权重是 `0.3 / 0.5 / 0.2`，价格信号占比最高，可能压制了基本面 alpha 的稳定性。可以尝试让基本面占更高比重，比如向 `0.4 / 0.2 / 0.4` 一类结构测试。\n\n5. **控制换手**  \n   可通过以下方式降低 turnover 并提升 fitness：\n   - 延长时间窗口\n   - 使用 `ts_decay_linear` 或平滑算子\n   - 减少对短周期 close 变化的依赖\n\n6. **检查 failed checks 的具体原因**  \n   这是最优先要处理的。如果是：\n   - 自相关过高：增加多样性、降低平滑重复\n   - 与已有因子相关性过高：替换价格反转部分\n   - 偏度/集中度问题：做截尾和中性化\n\n如果你愿意，我可以进一步基于这条表达式，直接给你改写出 **2~3 个更可能通过检查的 BRAIN alpha 版本**。"
    }
  }
]